README.md
setup.py
none/__init__.py
none/argparse.py
none/command.py
none/default_config.py
none/exceptions.py
none/helpers.py
none/log.py
none/message.py
none/natural_language.py
none/notice_request.py
none/permission.py
none/sched.py
none/session.py
none/typing.py
none/plugins/__init__.py
none/plugins/base.py
none_bot.egg-info/PKG-INFO
none_bot.egg-info/SOURCES.txt
none_bot.egg-info/dependency_links.txt
none_bot.egg-info/requires.txt
none_bot.egg-info/top_level.txt