Metadata-Version: 2.1
Name: none-bot
Version: 0.5.1
Summary: An asynchronous QQ bot framework based on CoolQ.
Home-page: https://github.com/richardchien/none-bot
Author: Richard Chien
Author-email: richardchienthebest@gmail.com
License: MIT License
Platform: any
Classifier: Development Status :: 4 - Beta
Classifier: Framework :: Robot Framework
Classifier: Framework :: Robot Framework :: Library
Classifier: License :: OSI Approved :: MIT License
Classifier: Operating System :: OS Independent
Classifier: Programming Language :: Python :: 3
Classifier: Programming Language :: Python :: 3 :: Only
Classifier: Programming Language :: Python :: 3.6
Classifier: Programming Language :: Python :: 3.7
Requires-Python: >=3.6
Provides-Extra: scheduler
